ListOperationsByUT/__init__.py
ListOperationsByUT/main.py
ListOperationsByUT-0.0.1.dist-info/LICENSE
ListOperationsByUT-0.0.1.dist-info/METADATA
ListOperationsByUT-0.0.1.dist-info/WHEEL
ListOperationsByUT-0.0.1.dist-info/top_level.txt
ListOperationsByUT-0.0.1.dist-info/RECORD
