Metadata-Version: 2.1
Name: ListOperationsByUT
Version: 0.0.1
Summary: A small python package for list operations.
Home-page: https://github.com/TewariUtkarsh/DerivedDtypes-Package
Author: Utkarsh Tewari
Author-email: tewariutkarsh@outlook.com
License: UNKNOWN
Project-URL: Bug Tracker, https://github.com/TewariUtkarsh/DerivedDtypes-Package/issues
Platform: UNKNOWN
Classifier: Programming Language :: Python :: 3
Classifier: License :: OSI Approved :: MIT License
Classifier: Operating System :: OS Independent
Requires-Python: >=3.6
License-File: LICENSE
